setup.py
diepy/MultipartPostHandler.py
diepy/__init__.py
diepy/cli.py
diepy/core.py
diepy/mail.py
diepy.egg-info/PKG-INFO
diepy.egg-info/SOURCES.txt
diepy.egg-info/dependency_links.txt
diepy.egg-info/entry_points.txt
diepy.egg-info/not-zip-safe
diepy.egg-info/requires.txt
diepy.egg-info/top_level.txt
tests/__init__.py
tests/diepy_tests.py