Metadata-Version: 1.1
Name: diepy
Version: 0.7.1
Summary: database import export utility
Home-page: https://github.com/3nth/diepy
Author: Derek Flenniken
Author-email: derek.flenniken@ucsf.edu
License: MIT License
Download-URL: https://github.com/3nth/diepy
Platform: any
Classifier: Programming Language :: Python
Classifier: Development Status :: 4 - Beta
Classifier: Natural Language :: English
Classifier: Environment :: Console
Classifier: Intended Audience :: Developers
Classifier: License :: OSI Approved :: MIT License
Classifier: Operating System :: OS Independent
Classifier: Topic :: Database
Classifier: Topic :: Software Development :: Libraries :: Python Modules
